raspi_sensor/__init__.py
raspi_sensor/config.py
raspi_sensor/exceptions.py
raspi_sensor/logging.py
raspi_sensor/main.py
raspi_sensor/mqtt.py
raspi_sensor/sensor.cfg.example
raspi_sensor/sensor.py
raspi_sensor/zabbix.py
RPi.Sensor-0.5.3.dist-info/LICENSE
RPi.Sensor-0.5.3.dist-info/METADATA
RPi.Sensor-0.5.3.dist-info/WHEEL
RPi.Sensor-0.5.3.dist-info/top_level.txt
RPi.Sensor-0.5.3.dist-info/RECORD
